loveread/__init__.py
loveread/__main__.py
loveread/loveread.py
loveread-0.2.8.dist-info/LICENSE
loveread-0.2.8.dist-info/METADATA
loveread-0.2.8.dist-info/WHEEL
loveread-0.2.8.dist-info/top_level.txt
loveread-0.2.8.dist-info/RECORD
