Metadata-Version: 2.1
Name: loveread
Version: 0.2.8
Summary: A brief description of your package
Home-page: https://gitlab.com/wladgavrilov/loveread
Author: Vlad Havrylov
Author-email: wladgavrilov@gmail.com
Classifier: License :: OSI Approved :: MIT License
Classifier: Programming Language :: Python
Classifier: Programming Language :: Python :: 3
Classifier: Programming Language :: Python :: 3.7
License-File: LICENSE
Requires-Dist: bs4
